fileserver/__init__.py
fileserver/asgi.cpython-37m-x86_64-linux-gnu.so
fileserver/middleware.cpython-37m-x86_64-linux-gnu.so
fileserver/settings.cpython-37m-x86_64-linux-gnu.so
fileserver/urls.cpython-37m-x86_64-linux-gnu.so
fileserver/wsgi.cpython-37m-x86_64-linux-gnu.so
fileserver/api/__init__.py
fileserver/api/apps.cpython-37m-x86_64-linux-gnu.so
fileserver/api/exceptions.cpython-37m-x86_64-linux-gnu.so
fileserver/api/interfaces/__init__.py
fileserver/api/interfaces/github_export.cpython-37m-x86_64-linux-gnu.so
fileserver/api/interfaces/github_import.cpython-37m-x86_64-linux-gnu.so
fileserver/api/interfaces/github_issue.cpython-37m-x86_64-linux-gnu.so
fileserver/api/migrations/__init__.py
fileserver/api/models/__init__.py
fileserver/api/models/directory.cpython-37m-x86_64-linux-gnu.so
fileserver/api/models/github.cpython-37m-x86_64-linux-gnu.so
fileserver/api/models/model_directory.cpython-37m-x86_64-linux-gnu.so
fileserver/api/views/__init__.py
fileserver/api/views/directory_view.cpython-37m-x86_64-linux-gnu.so
fileserver/api/views/file_view.cpython-37m-x86_64-linux-gnu.so
fileserver/api/views/github_view.cpython-37m-x86_64-linux-gnu.so
fileserver/api/views/json_model_view.cpython-37m-x86_64-linux-gnu.so
fileserver/api/views/model_directory_view.cpython-37m-x86_64-linux-gnu.so
fileserver/api/views/url_reachable.cpython-37m-x86_64-linux-gnu.so
fileserver/api/views/util.cpython-37m-x86_64-linux-gnu.so
fileserver/api/views/version_view.cpython-37m-x86_64-linux-gnu.so
perceptilabs/CoreThread.cpython-37m-x86_64-linux-gnu.so
perceptilabs/__init__.py
perceptilabs/app_variables.json
perceptilabs/azure.cpython-37m-x86_64-linux-gnu.so
perceptilabs/coreInterface.cpython-37m-x86_64-linux-gnu.so
perceptilabs/createDataObject.cpython-37m-x86_64-linux-gnu.so
perceptilabs/dataevents.cpython-37m-x86_64-linux-gnu.so
perceptilabs/extractVariables.cpython-37m-x86_64-linux-gnu.so
perceptilabs/funclib.cpython-37m-x86_64-linux-gnu.so
perceptilabs_gpu-0.11.11.dist-info/METADATA
perceptilabs_gpu-0.11.11.dist-info/WHEEL
perceptilabs_gpu-0.11.11.dist-info/entry_points.txt
perceptilabs_gpu-0.11.11.dist-info/top_level.txt
perceptilabs_gpu-0.11.11.dist-info/RECORD
